todecoratorfactory/__init__.py
todecoratorfactory/__main__.py
todecoratorfactory/tests/__init__.py
todecoratorfactory/tests/test_1984.py
todecoratorfactory-0.0.0.dev0.dist-info/LICENSE.txt
todecoratorfactory-0.0.0.dev0.dist-info/METADATA
todecoratorfactory-0.0.0.dev0.dist-info/WHEEL
todecoratorfactory-0.0.0.dev0.dist-info/top_level.txt
todecoratorfactory-0.0.0.dev0.dist-info/RECORD
